autonomize_sdk/__init__.py
autonomize_sdk/telemetry/README.md
autonomize_sdk/telemetry/__init__.py
autonomize_sdk/telemetry/constants.py
autonomize_sdk/telemetry/core/__init__.py
autonomize_sdk/telemetry/services/__init__.py
autonomize_sdk/telemetry/services/logging_service.py
autonomize_sdk/telemetry/services/metrics_service.py
autonomize_sdk/telemetry/services/tracing_service.py
autonomize_sdk/telemetry/types.py
autonomize_sdk_python-0.0.4.dist-info/METADATA
autonomize_sdk_python-0.0.4.dist-info/WHEEL
autonomize_sdk_python-0.0.4.dist-info/RECORD
